kenar/__init__.py
kenar/addon.py
kenar/app.py
kenar/asset.py
kenar/chatmessage.py
kenar/events.py
kenar/finder.py
kenar/icons.py
kenar/image.py
kenar/oauth.py
kenar/request.py
kenar/models/__init__.py
kenar/widgets/__init__.py
kenar/widgets/action.py
kenar/widgets/base.py
kenar/widgets/color.py
kenar/widgets/description_row.py
kenar/widgets/evaluation_row.py
kenar/widgets/event_row.py
kenar/widgets/group_info_row.py
kenar/widgets/image_carousel_row.py
kenar/widgets/score_row.py
kenar/widgets/selector_row.py
kenar/widgets/subtitle_row.py
kenar/widgets/title_row.py
kenar/widgets/wide_button_bar.py
kenar/widgets/widget_type.py
kenar-0.7.1.dist-info/licenses/LICENSE.txt
samples/__init__.py
samples/sample_addon.py
samples/sample_app.py
samples/sample_asset.py
samples/sample_chat.py
samples/sample_finder.py
samples/sample_oauth.py
kenar-0.7.1.dist-info/METADATA
kenar-0.7.1.dist-info/WHEEL
kenar-0.7.1.dist-info/top_level.txt
kenar-0.7.1.dist-info/RECORD
