Metadata-Version: 2.4
Name: Kenar
Version: 0.7.1
Summary: facilitate using kenar divar APIs
Home-page: https://github.com/divar-ir/kenar-api
Author: Kenar
Author-email: kenar@divar.ir
Classifier: Programming Language :: Python :: 3
Classifier: Operating System :: OS Independent
Requires-Python: >=3.10
License-File: LICENSE.txt
Requires-Dist: httpx>=0.26.0
Requires-Dist: pydantic>=2.6.0
Dynamic: author
Dynamic: author-email
Dynamic: classifier
Dynamic: description
Dynamic: description-content-type
Dynamic: home-page
Dynamic: license-file
Dynamic: requires-dist
Dynamic: requires-python
Dynamic: summary
